tc_grain/__init__.py
tc_grain/_version.py
tc_grain/chemcloud.py
tc_grain/chemcloud_trio_patch.py
tc_grain/tcpb.py
tc_grain/util.py
tc_grain-0.3.0.dist-info/METADATA
tc_grain-0.3.0.dist-info/WHEEL
tc_grain-0.3.0.dist-info/entry_points.txt
tc_grain-0.3.0.dist-info/top_level.txt
tc_grain-0.3.0.dist-info/RECORD
