Metadata-Version: 2.1
Name: tc-grain
Version: 0.3.0
Requires-Python: >=3.10
Requires-Dist: chemcloud
Requires-Dist: tcpb-trio
Requires-Dist: trio
Provides-Extra: dev
Requires-Dist: black; extra == "dev"
Requires-Dist: pre-commit; extra == "dev"
